zxbin2tap/__init__.py
zxbin2tap/bin2tap.py
zxbin2tap/cli.py
bin2tap-0.5.dist-info/METADATA
bin2tap-0.5.dist-info/WHEEL
bin2tap-0.5.dist-info/entry_points.txt
bin2tap-0.5.dist-info/top_level.txt
bin2tap-0.5.dist-info/RECORD
