Metadata-Version: 2.4
Name: bin2tap
Version: 0.5
Summary: Convert a binary file into ZX Spectrum TAP file
Home-page: https://github.com/rtorralba/bin2tap
Author: Raül Torralba
Dynamic: author
Dynamic: description
Dynamic: description-content-type
Dynamic: home-page
Dynamic: summary
